{
  "meta": {
    "title": "微服务架构",
    "description": "微服务设计模式、服务治理与分布式系统",
    "icon": "server"
  },
  "sections": [
    {
      "type": "keyPoints",
      "title": "核心要点",
      "items": [
        "服务拆分与边界划分",
        "服务注册与发现",
        "熔断降级与限流",
        "分布式事务与一致性"
      ]
    },
    {
      "type": "text",
      "title": "概述",
      "content": "微服务架构将单体应用拆分为多个独立服务，每个服务专注于特定业务能力。这种架构提高了系统的可扩展性和可维护性，但也带来了分布式系统的复杂性。"
    },
    {
      "type": "flow",
      "title": "微服务架构组件",
      "subtitle": "典型微服务架构的核心组件",
      "direction": "horizontal",
      "steps": [
        { "label": "网关", "description": "API Gateway", "color": "bg-purple-500" },
        { "label": "服务发现", "description": "注册中心", "color": "bg-blue-500" },
        { "label": "服务", "description": "业务服务", "color": "bg-cyan-500" },
        { "label": "配置中心", "description": "Config Server", "color": "bg-green-500" },
        { "label": "监控", "description": "可观测性", "color": "bg-yellow-500" }
      ]
    },
    {
      "type": "cards",
      "title": "设计模式",
      "layout": "grid",
      "columns": 3,
      "items": [
        {
          "title": "服务发现",
          "badge": "基础",
          "badgeColor": "green",
          "points": [
            "客户端发现",
            "服务端发现",
            "Consul/Nacos/etcd"
          ]
        },
        {
          "title": "熔断器",
          "badge": "容错",
          "badgeColor": "blue",
          "points": [
            "Circuit Breaker 模式",
            "快速失败",
            "自动恢复"
          ]
        },
        {
          "title": "限流",
          "badge": "保护",
          "badgeColor": "amber",
          "points": [
            "令牌桶/漏桶",
            "滑动窗口",
            "分布式限流"
          ]
        },
        {
          "title": "Saga 模式",
          "badge": "事务",
          "badgeColor": "purple",
          "points": [
            "分布式事务",
            "补偿机制",
            "最终一致性"
          ]
        },
        {
          "title": "CQRS",
          "badge": "架构",
          "badgeColor": "purple",
          "points": [
            "读写分离",
            "命令查询分离",
            "事件溯源"
          ]
        },
        {
          "title": "Sidecar",
          "badge": "部署",
          "badgeColor": "red",
          "points": [
            "服务网格",
            "代理模式",
            "Istio/Linkerd"
          ]
        }
      ]
    },
    {
      "type": "table",
      "title": "技术选型",
      "highlightFirst": true,
      "headers": ["类别", "开源方案", "云服务"],
      "rows": [
        ["服务发现", "Consul, Nacos, etcd", "AWS Cloud Map"],
        ["API 网关", "Kong, APISIX", "AWS API Gateway"],
        ["熔断限流", "Sentinel, Hystrix", "AWS WAF"],
        ["配置中心", "Apollo, Nacos", "AWS AppConfig"],
        ["链路追踪", "Jaeger, Zipkin", "AWS X-Ray"]
      ]
    },
    {
      "type": "list",
      "title": "最佳实践",
      "style": "check",
      "items": [
        { "label": "领域驱动设计", "description": "基于业务领域划分服务边界" },
        { "label": "契约优先", "description": "先定义接口契约再实现" },
        { "label": "弹性设计", "description": "考虑失败场景，实现容错" },
        { "label": "可观测性", "description": "日志、指标、追踪三位一体" }
      ]
    }
  ],
  "relatedTopics": ["Kubernetes", "服务网格", "分布式系统"],
  "articles": [
    {
      "slug": "patterns",
      "title": "微服务设计模式",
      "description": "常用微服务设计模式与实践",
      "priority": "recommended"
    },
    {
      "slug": "discovery",
      "title": "服务发现",
      "description": "服务注册与发现机制",
      "priority": "essential"
    },
    {
      "slug": "circuit-breaker",
      "title": "熔断与降级",
      "description": "熔断器模式与弹性设计",
      "priority": "important"
    },
    {
      "slug": "service-mesh",
      "title": "服务网格",
      "description": "Service Mesh 架构、Istio 实践与流量管理",
      "priority": "important"
    }
  ]
}
